tsel/__init__.py
tsel/__main__.py
tsel/utils.py
tsel-0.0.13.dist-info/LICENSE
tsel-0.0.13.dist-info/METADATA
tsel-0.0.13.dist-info/WHEEL
tsel-0.0.13.dist-info/entry_points.txt
tsel-0.0.13.dist-info/top_level.txt
tsel-0.0.13.dist-info/RECORD
