Metadata-Version: 2.1
Name: tsel
Version: 0.0.13
Summary: tsel - A small CLI tool for tabular data
Author-email: Davur <davur@davur.net>
Project-URL: Homepage, https://github.com/davur/tsel
Project-URL: Issues, https://github.com/davur/tsel/issues
Classifier: Programming Language :: Python :: 3
Classifier: License :: OSI Approved :: MIT License
Classifier: Operating System :: OS Independent
Requires-Python: >=3.8
License-File: LICENSE
Requires-Dist: docopt >0.6
